gluerpy/__init__.py
gluerpy/client.py
gluerpy/client_redis.py
gluerpy/lib/__init__.py
gluerpy/lib/acl.py
gluerpy/lib/redis_lib.py
gluerpy-1.0.28.dist-info/METADATA
gluerpy-1.0.28.dist-info/WHEEL
gluerpy-1.0.28.dist-info/top_level.txt
gluerpy-1.0.28.dist-info/RECORD
