Metadata-Version: 2.4
Name: gluerpy
Version: 1.0.28
Summary: Python library to connect to gluer services
Home-page: https://www.gluer.io
Author: Thiago Magro
Author-email: thiago.magro@gmail.com
Classifier: Programming Language :: Python :: 3
Classifier: License :: OSI Approved :: MIT License
Classifier: Operating System :: OS Independent
Requires-Python: >=3.6
Requires-Dist: redis
Dynamic: author
Dynamic: author-email
Dynamic: classifier
Dynamic: description
Dynamic: description-content-type
Dynamic: home-page
Dynamic: requires-dist
Dynamic: requires-python
Dynamic: summary
